Metadata-Version: 2.1
Name: TempCleaner
Version: 0.1.5
Summary: The "TempCleaner" application provides a simple and user-friendly interface that allows users to quickly scan their computer for temporary files and folders.
Author: Kartikey Baghel
Author-email: kartikeybaghel@hotmail.com
Keywords: clean temp,TempCleaner,Temp Clean,Temp Cleaner,temp,clean,temporary,temporary files clean,windows,window,clean temporary file,clean temporary file for windows
Classifier: Development Status :: 1 - Planning
Classifier: Intended Audience :: Developers
Classifier: Programming Language :: Python :: 3
Classifier: Operating System :: Unix
Classifier: Operating System :: Microsoft :: Windows
